README.txt
setup.py
collective/__init__.py
collective.contextualcontactinfo.egg-info/PKG-INFO
collective.contextualcontactinfo.egg-info/SOURCES.txt
collective.contextualcontactinfo.egg-info/dependency_links.txt
collective.contextualcontactinfo.egg-info/entry_points.txt
collective.contextualcontactinfo.egg-info/namespace_packages.txt
collective.contextualcontactinfo.egg-info/not-zip-safe
collective.contextualcontactinfo.egg-info/requires.txt
collective.contextualcontactinfo.egg-info/top_level.txt
collective/contextualcontactinfo/__init__.py
collective/contextualcontactinfo/configure.zcml
collective/contextualcontactinfo/i18n.sh
collective/contextualcontactinfo/skins.zcml
collective/contextualcontactinfo/tests.py
collective/contextualcontactinfo/locales/collective.contextualcontactinfo.pot
collective/contextualcontactinfo/locales/it/LC_MESSAGES/collective.contextualcontactinfo.mo
collective/contextualcontactinfo/locales/it/LC_MESSAGES/collective.contextualcontactinfo.po
collective/contextualcontactinfo/profiles/default/actions.xml
collective/contextualcontactinfo/profiles/default/skins.xml
collective/contextualcontactinfo/skins/collective.contextualcontactinfo.templates/contact-info.cpt
collective/contextualcontactinfo/skins/collective.contextualcontactinfo.templates/contact-info.cpt.metadata
collective/contextualcontactinfo/skins/collective.contextualcontactinfo.templates/send_feedback_site.cpy
collective/contextualcontactinfo/skins/collective.contextualcontactinfo.templates/send_feedback_site.cpy.metadata
collective/contextualcontactinfo/skins/collective.contextualcontactinfo.templates/site_feedback_template.pt
docs/HISTORY.txt
docs/INSTALL.txt
docs/LICENSE.GPL
docs/LICENSE.txt