Metadata-Version: 1.0
Name: collective.contextualcontactinfo
Version: 0.1.0
Summary: Add the information about the context in contact-info message of your Plone Site
Home-page: http://plone.org/products/collective.contextualcontactinfo
Author: RedTurtle Technology
Author-email: sviluppoplone@redturtle.it
License: GPL
Keywords: contact-info plonegov message
Platform: UNKNOWN
Classifier: Framework :: Plone
Classifier: Framework :: Plone :: 3.3
Classifier: Framework :: Plone :: 4.0
Classifier: Framework :: Plone :: 4.1
Classifier: Programming Language :: Python
